simpleDB.py
simpleSQLiteDB-1.1.1.dist-info/LICENSE.txt
simpleSQLiteDB-1.1.1.dist-info/METADATA
simpleSQLiteDB-1.1.1.dist-info/WHEEL
simpleSQLiteDB-1.1.1.dist-info/top_level.txt
simpleSQLiteDB-1.1.1.dist-info/RECORD
